ser_mail_api/__init__.py
ser_mail_api/v1/__init__.py
ser_mail_api/v1/client.py
ser_mail_api/v1/common/__init__.py
ser_mail_api/v1/common/region.py
ser_mail_api/v1/data/__init__.py
ser_mail_api/v1/data/attachment.py
ser_mail_api/v1/data/content.py
ser_mail_api/v1/data/mailuser.py
ser_mail_api/v1/data/message.py
ser_mail_api/v1/data/message_headers.py
ser_mail_api/v1/data/result.py
ser_mail_api/v1/endpoints/__init__.py
ser_mail_api/v1/endpoints/send.py
ser_mail_api/v1/resources/__init__.py
ser_mail_api/v1/resources/dictionary.py
ser_mail_api/v1/resources/dictionary_resource.py
ser_mail_api/v1/resources/error_handler.py
ser_mail_api/v1/resources/filter_options.py
ser_mail_api/v1/resources/parameter.py
ser_mail_api/v1/resources/resource.py
ser_mail_api/v1/resources/resources.py
ser_mail_api/v1/resources/response_wrapper.py
ser_mail_api-2.0.6.dist-info/licenses/LICENSE
ser_mail_api-2.0.6.dist-info/METADATA
ser_mail_api-2.0.6.dist-info/WHEEL
ser_mail_api-2.0.6.dist-info/top_level.txt
ser_mail_api-2.0.6.dist-info/RECORD
