Metadata-Version: 2.4
Name: ser-mail-api
Version: 2.0.6
Summary: Proofpoint Secure Email Relay Mail API
License: MIT
Project-URL: repository, https://github.com/pfptcommunity/ser-mail-api-python
Project-URL: homepage, https://api-docs.ser.proofpoint.com/docs/email-submission
Requires-Python: >3.9
License-File: LICENSE
Requires-Dist: requests
Requires-Dist: requests-oauth2client
Requires-Dist: pysocks
Dynamic: license-file
